[
  {
    "date": "2024-06-20",
    "marketName": "MAIN BAZAR",
    "openNumber": "124",
    "jodiResult": "48",
    "closeNumber": "445"
  },
  {
    "date": "2024-06-21",
    "marketName": "MAIN BAZAR",
    "openNumber": "235",
    "jodiResult": "56",
    "closeNumber": "667"
  },
  {
    "date": "2024-06-22",
    "marketName": "MAIN BAZAR",
    "openNumber": "123",
    "jodiResult": "34",
    "closeNumber": "456"
  },
  {
    "date": "2025-06-25",
    "marketName": "MAIN BAZAR",
    "openNumber": "145",
    "jodiResult": "38",
    "closeNumber": "578"
  }
]
